question_creation_app_realpython/User.sqlite3
question_creation_app_realpython/User.txt
question_creation_app_realpython/__main__.py
question_creation_app_realpython/auth.py
question_creation_app_realpython/data_process.py
question_creation_app_realpython/load_data.py
question_creation_app_realpython/requirements.txt
question_creation_app_realpython/cloud_backup/User.sqlite3
question_creation_app_realpython/react/build/asset-manifest.json
question_creation_app_realpython/react/build/favicon.ico
question_creation_app_realpython/react/build/index.html
question_creation_app_realpython/react/build/logo192.png
question_creation_app_realpython/react/build/logo512.png
question_creation_app_realpython/react/build/manifest.json
question_creation_app_realpython/react/build/robots.txt
question_creation_app_realpython/react/build/static/css/2.9a2a5986.chunk.css
question_creation_app_realpython/react/build/static/css/2.9a2a5986.chunk.css.map
question_creation_app_realpython/react/build/static/css/main.605b9150.chunk.css
question_creation_app_realpython/react/build/static/css/main.605b9150.chunk.css.map
question_creation_app_realpython/react/build/static/js/2.8705c7e6.chunk.js
question_creation_app_realpython/react/build/static/js/2.8705c7e6.chunk.js.LICENSE.txt
question_creation_app_realpython/react/build/static/js/2.8705c7e6.chunk.js.map
question_creation_app_realpython/react/build/static/js/3.94c7fce7.chunk.js
question_creation_app_realpython/react/build/static/js/3.94c7fce7.chunk.js.map
question_creation_app_realpython/react/build/static/js/main.4cadf675.chunk.js
question_creation_app_realpython/react/build/static/js/main.4cadf675.chunk.js.map
question_creation_app_realpython/react/build/static/js/runtime-main.a048ddd9.js
question_creation_app_realpython/react/build/static/js/runtime-main.a048ddd9.js.map
question_creation_app_realpython/react/build/static/media/KaTeX_AMS-Regular.1436d720.ttf
question_creation_app_realpython-0.2.dist-info/LICENSE.txt
question_creation_app_realpython-0.2.dist-info/METADATA
question_creation_app_realpython-0.2.dist-info/WHEEL
question_creation_app_realpython-0.2.dist-info/entry_points.txt
question_creation_app_realpython-0.2.dist-info/top_level.txt
question_creation_app_realpython-0.2.dist-info/RECORD
